Workbook

Sheet QA_Report
A1: Finance Report Checker - QA Report
A3: Workbook | B3: sample_finance_report_large.xlsx
A4: Risk Score | B4: 38
A5: Risk Level | B5: high
A6: Executive Summary | B6: The workbook contains 9 potential issues: 1 high, 7 medium, and 1 low. The main risks are hardcoded values among formulas, total formulas that may omit detail rows, large period-over-period variances, formula inconsistencies, and blank cells between values.
A7: High Issues | B7: 1
A8: Medium Issues | B8: 7
A9: Low Issues | B9: 1
A12: Sheet Statistics
A13: Sheet | B13: Used Range | C13: Non-empty Cells | D13: Formula Cells | E13: Numeric Constant Cells | F13: Blank Cells Inside Used Range
A14: P&L Monthly | B14: A1:N16 | C14: 223 | D14: 110 | E14: 84 | F14: 1
A15: OPEX Detail | B15: A1:N9 | C15: 126 | D15: 20 | E15: 84 | F15: 0
A16: Reconciliation | B16: A1:N7 | C16: 98 | D16: 78 | E16: 0 | F16: 0
A17: Sources | B17: A1:D3 | C17: 12 | D17: 0 | E17: 0 | F17: 0
A20: Issues
A21: Severity | B21: Type | C21: Sheet | D21: Cell | E21: Metric | F21: Period | G21: Message | H21: Business Impact | I21: Suggested Fix
A22: medium | B22: formula_inconsistency_in_row | C22: P&L Monthly | D22: E4 | E22: Total Net Sales | F22: Apr | G22: Formula pattern differs from neighboring formulas in the same row. | H22: This may affect the reliability of the financial report. | I22: Review whether this formula should match the copied pattern used nearby.
A23: medium | B23: hardcoded_value_among_formulas | C23: P&L Monthly | D23: D8 | E23: Gross Margin | F23: Mar | G23: Numeric constant found in a row that mostly contains formulas. | H23: This may affect the reliability of the financial report. | I23: Check whether this value should be a formula copied from adjacent periods.
A24: low | B24: blank_cell_between_values | C24: P&L Monthly | D24: G9 | E24: Research & Development | F24: Jun | G24: Blank cell found between non-empty cells in the same row. | H24: This may affect the reliability of the financial report. | I24: Check whether this blank cell should contain a value or formula.
A25: medium | B25: variance_spike_between_periods | C25: P&L Monthly | D25: J10 | E25: Selling, General & Administrative | F25: Sep | G25: Value changed by more than 50% compared with the previous period. | H25: This may affect the reliability of the financial report. | I25: Review whether this period-over-period movement is expected and properly explained.
A26: medium | B26: variance_spike_between_periods | C26: P&L Monthly | D26: K10 | E26: Selling, General & Administrative | F26: Oct | G26: Value changed by more than 50% compared with the previous period. | H26: This may affect the reliability of the financial report. | I26: Review whether this period-over-period movement is expected and properly explained.
A27: medium | B27: formula_inconsistency_in_row | C27: P&L Monthly | D27: K12 | E27: Operating Income | F27: Oct | G27: Formula pattern differs from neighboring formulas in the same row. | H27: This may affect the reliability of the financial report. | I27: Review whether this formula should match the copied pattern used nearby.
A28: medium | B28: variance_spike_between_periods | C28: OPEX Detail | D28: J8 | E28: Other G&A | F28: Sep | G28: Value changed by more than 50% compared with the previous period. | H28: This may affect the reliability of the financial report. | I28: Review whether this period-over-period movement is expected and properly explained.
A29: medium | B29: variance_spike_between_periods | C29: OPEX Detail | D29: K8 | E29: Other G&A | F29: Oct | G29: Value changed by more than 50% compared with the previous period. | H29: This may affect the reliability of the financial report. | I29: Review whether this period-over-period movement is expected and properly explained.
A30: high | B30: total_formula_mismatch | C30: OPEX Detail | D30: F9 | E30: Total OPEX Detail | F30: May | G30: Total formula may not include all expected detail rows. | H30: This may affect operating expense analysis. | I30: Review whether the total formula includes all relevant detail rows for this period.

Sheet P&L Monthly
A1: Metric | B1: Jan | C1: Feb | D1: Mar | E1: Apr | F1: May | G1: Jun | H1: Jul | I1: Aug | J1: Sep | K1: Oct | L1: Nov | M1: Dec | N1: FY Total | P1: Test Case Notes | Q1: Expected Detection | R1: Purpose
A2: Net Sales - Products | B2: 25000 | C2: 23500 | D2: 24000 | E2: 26000 | F2: 25500 | G2: 25000 | H2: 24500 | I2: 24800 | J2: 26000 | K2: 27000 | L2: 28000 | M2: 28961 | N2: =SUM(B2:M2) | P2: D8 hardcoded as 15500 | Q2: hardcoded_value_among_formulas | R2: Gross Margin formula row has one manual value
A3: Net Sales - Services | B3: 7600 | C3: 7800 | D3: 7900 | E3: 8000 | F3: 8100 | G3: 8200 | H3: 8300 | I3: 8350 | J3: 8400 | K3: 8500 | L3: 8600 | M3: 8660 | N3: =SUM(B3:M3) | P3: G9 blank | Q3: blank_cell_between_values | R3: R&D row has a blank month between numeric values
A4: Total Net Sales | B4: =B2+B3 | C4: =C2+C3 | D4: =D2+D3 | E4: =E2+E2 | F4: =F2+F3 | G4: =G2+G3 | H4: =H2+H3 | I4: =I2+I3 | J4: =J2+J3 | K4: =K2+K3 | L4: =L2+L3 | M4: =M2+M3 | N4: =SUM(B4:M4) | P4: I10 SG&A spike to -5200 | Q4: variance_spike_between_periods | R4: Unusual SG&A movement vs prior period
A5: Cost of Sales - Products | B5: -14000 | C5: -13200 | D5: -13500 | E5: -14500 | F5: -14200 | G5: -13900 | H5: -13600 | I5: -13750 | J5: -14400 | K5: -14900 | L5: -15400 | M5: -15960 | N5: =SUM(B5:M5) | P5: E4 formula =E2+E2 | Q5: formula_inconsistency_in_row | R5: Total Net Sales formula inconsistency
A6: Cost of Sales - Services | B6: -2300 | C6: -2350 | D6: -2380 | E6: -2400 | F6: -2420 | G6: -2450 | H6: -2480 | I6: -2500 | J6: -2520 | K6: -2550 | L6: -2580 | M6: -2630 | N6: =SUM(B6:M6) | P6: K12 formula =K4+K11 | Q6: formula_inconsistency_in_row | R6: Operating Income formula inconsistency
A7: Total Cost of Sales | B7: =B5+B6 | C7: =C5+C6 | D7: =D5+D6 | E7: =E5+E6 | F7: =F5+F6 | G7: =G5+G6 | H7: =H5+H6 | I7: =I5+I6 | ... M7: =M5+M6 | N7: =SUM(B7:M7) | P7: OPEX Detail F9 omits F8 | Q7: future_total_mismatch | R7: Subtotal mismatch for future total/subtotal rule
A8: Gross Margin | B8: =B4+B7 | C8: =C4+C7 | D8: 15500 | E8: =E4+E7 | F8: =F4+F7 | G8: =G4+G7 | H8: =H4+H7 | I8: =I4+I7 | J8: =J4+J7 | K8: =K4+K7 | L8: =L4+L7 | M8: =M4+M7 | N8: =SUM(B8:M8)
A9: Research & Development | B9: -2600 | C9: -2700 | D9: -2750 | E9: -2800 | F9: -2850 | H9: -2950 | I9: -3000 | J9: -3050 | K9: -3100 | L9: -3150 | M9: -3200 | N9: =SUM(B9:M9)
A10: Selling, General & Administrative | B10: -2100 | C10: -2150 | D10: -2200 | E10: -2250 | F10: -2300 | G10: -2350 | H10: -2400 | I10: -2450 | J10: -5200 | K10: -2550 | L10: -2600 | M10: -2650 | N10: =SUM(B10:M10)
A11: Total Operating Expenses | B11: =B9+B10 | C11: =C9+C10 | D11: =D9+D10 | E11: =E9+E10 | F11: =F9+F10 | G11: =G9+G10 | H11: =H9+H10 | I11: =I9+I10 | ... M11: =M9+M10 | N11: =SUM(B11:M11)
A12: Operating Income | B12: =B8+B11 | C12: =C8+C11 | D12: =D8+D11 | E12: =E8+E11 | F12: =F8+F11 | G12: =G8+G11 | H12: =H8+H11 | I12: =I8+I11 | J12: =J8+J11 | K12: =K4+K11 | L12: =L8+L11 | M12: =M8+M11 | N12: =SUM(B12:M12)
A13: Other Income/(Expense), Net | B13: 50 | C13: 40 | D13: -20 | E13: 30 | F13: 25 | G13: 10 | H13: -15 | I13: 20 | J13: 35 | K13: 45 | L13: 40 | M13: 69 | N13: =SUM(B13:M13)
A14: Income Before Tax | B14: =B12+B13 | C14: =C12+C13 | D14: =D12+D13 | E14: =E12+E13 | F14: =F12+F13 | G14: =G12+G13 | H14: =H12+H13 | I14: =I12+I13 | ... M14: =M12+M13 | N14: =SUM(B14:M14)
A15: Provision for Income Taxes | B15: =-B14*0.22 | C15: =-C14*0.22 | D15: =-D14*0.22 | E15: =-E14*0.22 | F15: =-F14*0.22 | G15: =-G14*0.22 | H15: =-H14*0.22 | I15: =-I14*0.22 | ... M15: =-M14*0.22 | N15: =SUM(B15:M15)
A16: Net Income | B16: =B14+B15 | C16: =C14+C15 | D16: =D14+D15 | E16: =E14+E15 | F16: =F14+F15 | G16: =G14+G15 | H16: =H14+H15 | I16: =I14+I15 | ... M16: =M14+M15 | N16: =SUM(B16:M16)

Sheet OPEX Detail
A1: Metric | B1: Jan | C1: Feb | D1: Mar | E1: Apr | F1: May | G1: Jun | H1: Jul | I1: Aug | J1: Sep | K1: Oct | L1: Nov | M1: Dec | N1: FY Total
A2: Payroll | B2: -900 | C2: -920 | D2: -930 | E2: -940 | F2: -950 | G2: -960 | H2: -970 | I2: -980 | J2: -990 | K2: -1000 | L2: -1010 | M2: -1020 | N2: =SUM(B2:M2)
A3: Marketing | B3: -450 | C3: -460 | D3: -470 | E3: -480 | F3: -490 | G3: -500 | H3: -510 | I3: -520 | J3: -530 | K3: -540 | L3: -550 | M3: -560 | N3: =SUM(B3:M3)
A4: IT & Cloud | B4: -220 | C4: -225 | D4: -230 | E4: -235 | F4: -240 | G4: -245 | H4: -250 | I4: -255 | J4: -260 | K4: -265 | L4: -270 | M4: -275 | N4: =SUM(B4:M4)
A5: Office & Rent | B5: -180 | C5: -180 | D5: -180 | E5: -180 | F5: -180 | G5: -180 | H5: -180 | I5: -180 | J5: -180 | K5: -180 | L5: -180 | M5: -180 | N5: =SUM(B5:M5)
A6: Professional Services | B6: -210 | C6: -220 | D6: -230 | E6: -240 | F6: -250 | G6: -260 | H6: -270 | I6: -280 | J6: -290 | K6: -300 | L6: -310 | M6: -320 | N6: =SUM(B6:M6)
A7: Travel & Events | B7: -90 | C7: -95 | D7: -100 | E7: -105 | F7: -110 | G7: -115 | H7: -120 | I7: -125 | J7: -130 | K7: -135 | L7: -140 | M7: -145 | N7: =SUM(B7:M7)
A8: Other G&A | B8: -50 | C8: -50 | D8: -60 | E8: -70 | F8: -80 | G8: -90 | H8: -100 | I8: -110 | J8: -2820 | K8: -130 | L8: -140 | M8: -150 | N8: =SUM(B8:M8)
A9: Total OPEX Detail | B9: =SUM(B2:B8) | C9: =SUM(C2:C8) | D9: =SUM(D2:D8) | E9: =SUM(E2:E8) | F9: =SUM(F2:F7) | G9: =SUM(G2:G8) | H9: =SUM(H2:H8) | I9: =SUM(I2:I8) | J9: =SUM(J2:J8) | K9: =SUM(K2:K8) | L9: =SUM(L2:L8) | M9: =SUM(M2:M8) | N9: =SUM(B9:M9)

Sheet Reconciliation
A1: Metric | B1: Jan | C1: Feb | D1: Mar | E1: Apr | F1: May | G1: Jun | H1: Jul | I1: Aug | J1: Sep | K1: Oct | L1: Nov | M1: Dec | N1: FY Total
A2: P&L SG&A | B2: ='P&L Monthly'!B10 | C2: ='P&L Monthly'!C10 | D2: ='P&L Monthly'!D10 | E2: ='P&L Monthly'!E10 | F2: ='P&L Monthly'!F10 | G2: ='P&L Monthly'!G10 | H2: ='P&L Monthly'!H10 | I2: ='P&L Monthly'!I10 | ... M2: ='P&L Monthly'!M10 | N2: =SUM(B2:M2)
A3: OPEX Detail Total | B3: ='OPEX Detail'!B9 | C3: ='OPEX Detail'!C9 | D3: ='OPEX Detail'!D9 | E3: ='OPEX Detail'!E9 | F3: ='OPEX Detail'!F9 | G3: ='OPEX Detail'!G9 | H3: ='OPEX Detail'!H9 | I3: ='OPEX Detail'!I9 | ... M3: ='OPEX Detail'!M9 | N3: =SUM(B3:M3)
A4: Difference | B4: =B2-B3 | C4: =C2-C3 | D4: =D2-D3 | E4: =E2-E3 | F4: =F2-F3 | G4: =G2-G3 | H4: =H2-H3 | I4: =I2-I3 | ... M4: =M2-M3 | N4: =SUM(B4:M4)
A5: P&L Total OPEX | B5: ='P&L Monthly'!B11 | C5: ='P&L Monthly'!C11 | D5: ='P&L Monthly'!D11 | E5: ='P&L Monthly'!E11 | F5: ='P&L Monthly'!F11 | G5: ='P&L Monthly'!G11 | H5: ='P&L Monthly'!H11 | I5: ='P&L Monthly'!I11 | ... M5: ='P&L Monthly'!M11 | N5: =SUM(B5:M5)
A6: R&D + OPEX Detail | B6: ='P&L Monthly'!B9+'OPEX Detail'!B9 | C6: ='P&L Monthly'!C9+'OPEX Detail'!C9 | D6: ='P&L Monthly'!D9+'OPEX Detail'!D9 | E6: ='P&L Monthly'!E9+'OPEX Detail'!E9 | F6: ='P&L Monthly'!F9+'OPEX Detail'!F9 | G6: ='P&L Monthly'!G9+'OPEX Detail'!G9 | H6: ='P&L Monthly'!H9+'OPEX Detail'!H9 | I6: ='P&L Monthly'!I9+'OPEX Detail'!I9 | ... M6: ='P&L Monthly'!M9+'OPEX Detail'!M9 | N6: =SUM(B6:M6)
A7: Difference vs P&L Total OPEX | B7: =B5-B6 | C7: =C5-C6 | D7: =D5-D6 | E7: =E5-E6 | F7: =F5-F6 | G7: =G5-G6 | H7: =H5-H6 | I7: =I5-I6 | ... M7: =M5-M6 | N7: =SUM(B7:M7)

Sheet Sources
A1: Source | B1: URL | C1: Notes | D1: Used for
A2: Apple FY2025 Q4 consolidated financial statements | B2: https://www.apple.com/newsroom/pdfs/fy2025-q4/FY25_Q4_Consolidated_Financial_Statements.pdf | C2: Public Apple consolidated financial statements. The workbook uses similar line-item structure and illustrative monthly allocations, not exact monthly Apple data. | D2: P&L line-item structure and annual scale references
A3: Apple 2024 Form 10-K / SEC filing | B3: https://www.sec.gov/Archives/edgar/data/320193/000032019324000123/aapl-20240928.htm | C3: Public SEC Form 10-K, used to validate that the selected financial statement line items are common in real company reporting. | D3: Revenue, cost of sales, operating expenses, tax structure
